README.rst
setup.py
httpclient_session/__init__.py
httpclient_session/cookies.py
httpclient_session/mocks.py
httpclient_session/sessions.py
httpclient_session/contrib/__init__.py
httpclient_session/contrib/cookies.py
httpclient_session/test/__init__.py
httpclient_session/test/testsuite.py
tornado_httpclient_session.egg-info/PKG-INFO
tornado_httpclient_session.egg-info/SOURCES.txt
tornado_httpclient_session.egg-info/dependency_links.txt
tornado_httpclient_session.egg-info/pbr.json
tornado_httpclient_session.egg-info/requires.txt
tornado_httpclient_session.egg-info/top_level.txt