Metadata-Version: 1.1
Name: tornado-httpclient-session
Version: 0.2.5
Summary: Session support to tornado.httpclient.
Home-page: https://github.com/mailto1587/tornado-httpclient-session
Author: mailto1587
Author-email: mailto1587@gmail.com
License: http://opensource.org/licenses/MIT
Keywords: Tornado,HttpClient,Session
Platform: UNKNOWN
Classifier: Programming Language :: Python :: 2
Classifier: Programming Language :: Python :: 3
